itch/__init__.py
itch/costume.py
itch/data_view.py
itch/event_receiver.py
itch/sched.py
itch/sprite.py
itch/stage.py
itch/utils.py
itch_framework-0.0.1.dist-info/DESCRIPTION.rst
itch_framework-0.0.1.dist-info/METADATA
itch_framework-0.0.1.dist-info/RECORD
itch_framework-0.0.1.dist-info/WHEEL
itch_framework-0.0.1.dist-info/metadata.json
itch_framework-0.0.1.dist-info/top_level.txt
