Metadata-Version: 2.0
Name: itch-framework
Version: 0.0.1
Summary: A Scratch-like environment for python
Home-page: https://github.com/danjpgriffin/itch
Author: Dan Griffin
Author-email: itch-framework@xiragon.com
License: GPLv3
Keywords: scratch education children
Platform: UNKNOWN
Classifier: Development Status :: 3 - Alpha
Classifier: Intended Audience :: Developers
Classifier: Intended Audience :: Education
Classifier: License :: OSI Approved :: GNU General Public License v3 (GPLv3)
Classifier: Programming Language :: Python :: 3.6
Requires-Dist: greenlet (>=0.4)
Requires-Dist: pygame (>=1.9)
